discard.py
discard-0.1.dist-info/LICENSE
discard-0.1.dist-info/WHEEL
discard-0.1.dist-info/METADATA
discard-0.1.dist-info/RECORD
