Metadata-Version: 2.1
Name: discard
Version: 0.1
Summary: Discard is a funny way to accumulate things that you  might use some day
Home-page: UNKNOWN
License: UNKNOWN
Author: Augusto Kielbowicz
Author-email: augusto.kiel@gmail.com
Classifier: License :: OSI Approved :: GNU General Public License v3 or later (GPLv3+)
